{
  "time_filters": {
    "asia": {
      "Monday": [
        6,
        7,
        8,
        9,
        17,
        19
      ],
      "Tuesday": [
        7,
        8,
        14,
        17,
        19
      ],
      "Wednesday": [
        6,
        7,
        9,
        10,
        11,
        12,
        13,
        14,
        19
      ],
      "Thursday": [
        6,
        9,
        11,
        13,
        15,
        16,
        19
      ],
      "Friday": [
        6,
        11,
        15
      ],
      "Saturday": []
    },
    "ny": {
      "Monday": [
        11,
        12,
        16
      ],
      "Tuesday": [
        7,
        9,
        11,
        13,
        15
      ],
      "Wednesday": [
        8,
        10,
        12,
        13
      ],
      "Thursday": [
        8,
        9,
        11,
        13,
        14
      ],
      "Friday": [
        9,
        10,
        14,
        15
      ],
      "Saturday": []
    }
  }
}