{
  "config": {
    "table": "gold_prices",
    "start_date": "2025-05-20",
    "end_date": "2026-04-10",
    "timeframe": "1min",
    "disable_time_filter": true,
    "window": 150,
    "window_15m": 0,
    "min_window_range": 40.0,
    "min_15m_drop": 15.0,
    "min_15m_rise": 0.0,
    "last_bar_wr90_high": null,
    "last_bar_wr90_low": null,
    "horizon": 25,
    "trend_threshold": 0.008,
    "adverse_limit": 15.0,
    "long_target_threshold": 0.006,
    "short_target_threshold": 0.008,
    "long_adverse_limit": 12.0,
    "short_adverse_limit": 18.0,
    "test_start_date": "2025-11-25T17:02:00+00:00",
    "test_size": 0.4,
    "max_samples": 12000,
    "optimize": false,
    "optimize_prob": false,
    "two_branch": false,
    "two_branch_stage": "both",
    "max_flat_ratio": 2.5,
    "classifier": "gradient_boosting",
    "stage1_min_prob": 0.48,
    "stage2_min_prob": 0.5,
    "stage2_min_prob_up": null,
    "stage2_min_prob_down": null,
    "stage1_min_prob_1m": null,
    "stage1_min_prob_15m": null,
    "stage2_min_prob_1m": null,
    "stage2_min_prob_15m": null,
    "use_state_features": true,
    "use_15m_wick_features": true,
    "wick_feature_min_range": 40.0,
    "wick_feature_min_pct": 35.0,
    "wick_feature_min_volume": 3000.0,
    "use_stage1_day_ohl_utc2": false,
    "state_oof_splits": 5,
    "pred_history_len": 150,
    "allow_overlap_backtest": false,
    "reverse_exit_prob": 0.7,
    "max_hold_minutes": null,
    "weak_periods_json": null,
    "eval_mode": "single_split",
    "wf_init_train_months": 6,
    "wf_retrain_days": 14,
    "wf_max_train_days": 365,
    "wf_min_train_samples": 300,
    "wf_disable_sweep": false,
    "wf_sweep_flat_ratios": [
      3.0,
      4.0,
      5.0
    ],
    "wf_sweep_stage1_probs": [],
    "wf_sweep_stage2_probs": [],
    "wf_sweep_stage2_long_probs": [],
    "wf_sweep_stage2_short_probs": [],
    "wf_sweep_val_ratio": 0.2,
    "wf_sweep_min_val_samples": 50,
    "wf_anchor_mode": "weekend_fri_close",
    "wf_cycle_model_dir": null,
    "wf_save_cycle_models": true,
    "prep_cache_dir": null,
    "refresh_prep_cache": false,
    "random_state": 42,
    "model_in": null,
    "model_out": "training/_tmp_verify_wick35.joblib",
    "report_out": "training/_tmp_verify_wick35.json",
    "trades_out": "training/_tmp_verify_wick35.csv"
  },
  "execution_semantics": {
    "signal_reference": "signal_bar_close",
    "entry_execution": "next_bar_open",
    "signal_price_field": "curr_close",
    "entry_price_field": "next_bar_open",
    "signal_time_field": "ts",
    "entry_time_field": "entry_time",
    "notes": "Labels and features stay anchored to the signal bar close, while simulated trade entries execute on the next bar open."
  },
  "threshold_used": 0.008,
  "horizon_used": 25,
  "long_target_threshold_used": 0.006,
  "short_target_threshold_used": 0.008,
  "long_adverse_limit_used": 12.0,
  "short_adverse_limit_used": 18.0,
  "min_window_range_used": 40.0,
  "window_15m": 0,
  "min_15m_drop": 15.0,
  "min_15m_rise": 0.0,
  "two_branch": false,
  "two_branch_stage": "both",
  "n_1m_feats": 1650,
  "use_state_features": true,
  "use_15m_wick_features": true,
  "wick_feature_min_range": 40.0,
  "wick_feature_min_pct": 35.0,
  "wick_feature_min_volume": 3000.0,
  "image_channel_names": [
    "open_rel",
    "high_rel",
    "low_rel",
    "close_rel",
    "body_rel",
    "range_rel",
    "vol_z",
    "vol_rel",
    "vol_diff_norm",
    "long_lower_wick_flag",
    "long_upper_wick_flag"
  ],
  "state_feature_names": [
    "pred_lag1_down",
    "pred_lag1_flat",
    "pred_lag1_up",
    "pred_lag2_down",
    "pred_lag2_flat",
    "pred_lag2_up",
    "pred_lag3_down",
    "pred_lag3_flat",
    "pred_lag3_up",
    "pred_lag4_down",
    "pred_lag4_flat",
    "pred_lag4_up",
    "pred_lag5_down",
    "pred_lag5_flat",
    "pred_lag5_up",
    "pred_lag6_down",
    "pred_lag6_flat",
    "pred_lag6_up",
    "pred_lag7_down",
    "pred_lag7_flat",
    "pred_lag7_up",
    "pred_lag8_down",
    "pred_lag8_flat",
    "pred_lag8_up",
    "pred_lag9_down",
    "pred_lag9_flat",
    "pred_lag9_up",
    "pred_lag10_down",
    "pred_lag10_flat",
    "pred_lag10_up",
    "pred_lag11_down",
    "pred_lag11_flat",
    "pred_lag11_up",
    "pred_lag12_down",
    "pred_lag12_flat",
    "pred_lag12_up",
    "pred_lag13_down",
    "pred_lag13_flat",
    "pred_lag13_up",
    "pred_lag14_down",
    "pred_lag14_flat",
    "pred_lag14_up",
    "pred_lag15_down",
    "pred_lag15_flat",
    "pred_lag15_up",
    "pred_lag16_down",
    "pred_lag16_flat",
    "pred_lag16_up",
    "pred_lag17_down",
    "pred_lag17_flat",
    "pred_lag17_up",
    "pred_lag18_down",
    "pred_lag18_flat",
    "pred_lag18_up",
    "pred_lag19_down",
    "pred_lag19_flat",
    "pred_lag19_up",
    "pred_lag20_down",
    "pred_lag20_flat",
    "pred_lag20_up",
    "pred_lag21_down",
    "pred_lag21_flat",
    "pred_lag21_up",
    "pred_lag22_down",
    "pred_lag22_flat",
    "pred_lag22_up",
    "pred_lag23_down",
    "pred_lag23_flat",
    "pred_lag23_up",
    "pred_lag24_down",
    "pred_lag24_flat",
    "pred_lag24_up",
    "pred_lag25_down",
    "pred_lag25_flat",
    "pred_lag25_up",
    "pred_lag26_down",
    "pred_lag26_flat",
    "pred_lag26_up",
    "pred_lag27_down",
    "pred_lag27_flat",
    "pred_lag27_up",
    "pred_lag28_down",
    "pred_lag28_flat",
    "pred_lag28_up",
    "pred_lag29_down",
    "pred_lag29_flat",
    "pred_lag29_up",
    "pred_lag30_down",
    "pred_lag30_flat",
    "pred_lag30_up",
    "pred_lag31_down",
    "pred_lag31_flat",
    "pred_lag31_up",
    "pred_lag32_down",
    "pred_lag32_flat",
    "pred_lag32_up",
    "pred_lag33_down",
    "pred_lag33_flat",
    "pred_lag33_up",
    "pred_lag34_down",
    "pred_lag34_flat",
    "pred_lag34_up",
    "pred_lag35_down",
    "pred_lag35_flat",
    "pred_lag35_up",
    "pred_lag36_down",
    "pred_lag36_flat",
    "pred_lag36_up",
    "pred_lag37_down",
    "pred_lag37_flat",
    "pred_lag37_up",
    "pred_lag38_down",
    "pred_lag38_flat",
    "pred_lag38_up",
    "pred_lag39_down",
    "pred_lag39_flat",
    "pred_lag39_up",
    "pred_lag40_down",
    "pred_lag40_flat",
    "pred_lag40_up",
    "pred_lag41_down",
    "pred_lag41_flat",
    "pred_lag41_up",
    "pred_lag42_down",
    "pred_lag42_flat",
    "pred_lag42_up",
    "pred_lag43_down",
    "pred_lag43_flat",
    "pred_lag43_up",
    "pred_lag44_down",
    "pred_lag44_flat",
    "pred_lag44_up",
    "pred_lag45_down",
    "pred_lag45_flat",
    "pred_lag45_up",
    "pred_lag46_down",
    "pred_lag46_flat",
    "pred_lag46_up",
    "pred_lag47_down",
    "pred_lag47_flat",
    "pred_lag47_up",
    "pred_lag48_down",
    "pred_lag48_flat",
    "pred_lag48_up",
    "pred_lag49_down",
    "pred_lag49_flat",
    "pred_lag49_up",
    "pred_lag50_down",
    "pred_lag50_flat",
    "pred_lag50_up",
    "pred_lag51_down",
    "pred_lag51_flat",
    "pred_lag51_up",
    "pred_lag52_down",
    "pred_lag52_flat",
    "pred_lag52_up",
    "pred_lag53_down",
    "pred_lag53_flat",
    "pred_lag53_up",
    "pred_lag54_down",
    "pred_lag54_flat",
    "pred_lag54_up",
    "pred_lag55_down",
    "pred_lag55_flat",
    "pred_lag55_up",
    "pred_lag56_down",
    "pred_lag56_flat",
    "pred_lag56_up",
    "pred_lag57_down",
    "pred_lag57_flat",
    "pred_lag57_up",
    "pred_lag58_down",
    "pred_lag58_flat",
    "pred_lag58_up",
    "pred_lag59_down",
    "pred_lag59_flat",
    "pred_lag59_up",
    "pred_lag60_down",
    "pred_lag60_flat",
    "pred_lag60_up",
    "pred_lag61_down",
    "pred_lag61_flat",
    "pred_lag61_up",
    "pred_lag62_down",
    "pred_lag62_flat",
    "pred_lag62_up",
    "pred_lag63_down",
    "pred_lag63_flat",
    "pred_lag63_up",
    "pred_lag64_down",
    "pred_lag64_flat",
    "pred_lag64_up",
    "pred_lag65_down",
    "pred_lag65_flat",
    "pred_lag65_up",
    "pred_lag66_down",
    "pred_lag66_flat",
    "pred_lag66_up",
    "pred_lag67_down",
    "pred_lag67_flat",
    "pred_lag67_up",
    "pred_lag68_down",
    "pred_lag68_flat",
    "pred_lag68_up",
    "pred_lag69_down",
    "pred_lag69_flat",
    "pred_lag69_up",
    "pred_lag70_down",
    "pred_lag70_flat",
    "pred_lag70_up",
    "pred_lag71_down",
    "pred_lag71_flat",
    "pred_lag71_up",
    "pred_lag72_down",
    "pred_lag72_flat",
    "pred_lag72_up",
    "pred_lag73_down",
    "pred_lag73_flat",
    "pred_lag73_up",
    "pred_lag74_down",
    "pred_lag74_flat",
    "pred_lag74_up",
    "pred_lag75_down",
    "pred_lag75_flat",
    "pred_lag75_up",
    "pred_lag76_down",
    "pred_lag76_flat",
    "pred_lag76_up",
    "pred_lag77_down",
    "pred_lag77_flat",
    "pred_lag77_up",
    "pred_lag78_down",
    "pred_lag78_flat",
    "pred_lag78_up",
    "pred_lag79_down",
    "pred_lag79_flat",
    "pred_lag79_up",
    "pred_lag80_down",
    "pred_lag80_flat",
    "pred_lag80_up",
    "pred_lag81_down",
    "pred_lag81_flat",
    "pred_lag81_up",
    "pred_lag82_down",
    "pred_lag82_flat",
    "pred_lag82_up",
    "pred_lag83_down",
    "pred_lag83_flat",
    "pred_lag83_up",
    "pred_lag84_down",
    "pred_lag84_flat",
    "pred_lag84_up",
    "pred_lag85_down",
    "pred_lag85_flat",
    "pred_lag85_up",
    "pred_lag86_down",
    "pred_lag86_flat",
    "pred_lag86_up",
    "pred_lag87_down",
    "pred_lag87_flat",
    "pred_lag87_up",
    "pred_lag88_down",
    "pred_lag88_flat",
    "pred_lag88_up",
    "pred_lag89_down",
    "pred_lag89_flat",
    "pred_lag89_up",
    "pred_lag90_down",
    "pred_lag90_flat",
    "pred_lag90_up",
    "pred_lag91_down",
    "pred_lag91_flat",
    "pred_lag91_up",
    "pred_lag92_down",
    "pred_lag92_flat",
    "pred_lag92_up",
    "pred_lag93_down",
    "pred_lag93_flat",
    "pred_lag93_up",
    "pred_lag94_down",
    "pred_lag94_flat",
    "pred_lag94_up",
    "pred_lag95_down",
    "pred_lag95_flat",
    "pred_lag95_up",
    "pred_lag96_down",
    "pred_lag96_flat",
    "pred_lag96_up",
    "pred_lag97_down",
    "pred_lag97_flat",
    "pred_lag97_up",
    "pred_lag98_down",
    "pred_lag98_flat",
    "pred_lag98_up",
    "pred_lag99_down",
    "pred_lag99_flat",
    "pred_lag99_up",
    "pred_lag100_down",
    "pred_lag100_flat",
    "pred_lag100_up",
    "pred_lag101_down",
    "pred_lag101_flat",
    "pred_lag101_up",
    "pred_lag102_down",
    "pred_lag102_flat",
    "pred_lag102_up",
    "pred_lag103_down",
    "pred_lag103_flat",
    "pred_lag103_up",
    "pred_lag104_down",
    "pred_lag104_flat",
    "pred_lag104_up",
    "pred_lag105_down",
    "pred_lag105_flat",
    "pred_lag105_up",
    "pred_lag106_down",
    "pred_lag106_flat",
    "pred_lag106_up",
    "pred_lag107_down",
    "pred_lag107_flat",
    "pred_lag107_up",
    "pred_lag108_down",
    "pred_lag108_flat",
    "pred_lag108_up",
    "pred_lag109_down",
    "pred_lag109_flat",
    "pred_lag109_up",
    "pred_lag110_down",
    "pred_lag110_flat",
    "pred_lag110_up",
    "pred_lag111_down",
    "pred_lag111_flat",
    "pred_lag111_up",
    "pred_lag112_down",
    "pred_lag112_flat",
    "pred_lag112_up",
    "pred_lag113_down",
    "pred_lag113_flat",
    "pred_lag113_up",
    "pred_lag114_down",
    "pred_lag114_flat",
    "pred_lag114_up",
    "pred_lag115_down",
    "pred_lag115_flat",
    "pred_lag115_up",
    "pred_lag116_down",
    "pred_lag116_flat",
    "pred_lag116_up",
    "pred_lag117_down",
    "pred_lag117_flat",
    "pred_lag117_up",
    "pred_lag118_down",
    "pred_lag118_flat",
    "pred_lag118_up",
    "pred_lag119_down",
    "pred_lag119_flat",
    "pred_lag119_up",
    "pred_lag120_down",
    "pred_lag120_flat",
    "pred_lag120_up",
    "pred_lag121_down",
    "pred_lag121_flat",
    "pred_lag121_up",
    "pred_lag122_down",
    "pred_lag122_flat",
    "pred_lag122_up",
    "pred_lag123_down",
    "pred_lag123_flat",
    "pred_lag123_up",
    "pred_lag124_down",
    "pred_lag124_flat",
    "pred_lag124_up",
    "pred_lag125_down",
    "pred_lag125_flat",
    "pred_lag125_up",
    "pred_lag126_down",
    "pred_lag126_flat",
    "pred_lag126_up",
    "pred_lag127_down",
    "pred_lag127_flat",
    "pred_lag127_up",
    "pred_lag128_down",
    "pred_lag128_flat",
    "pred_lag128_up",
    "pred_lag129_down",
    "pred_lag129_flat",
    "pred_lag129_up",
    "pred_lag130_down",
    "pred_lag130_flat",
    "pred_lag130_up",
    "pred_lag131_down",
    "pred_lag131_flat",
    "pred_lag131_up",
    "pred_lag132_down",
    "pred_lag132_flat",
    "pred_lag132_up",
    "pred_lag133_down",
    "pred_lag133_flat",
    "pred_lag133_up",
    "pred_lag134_down",
    "pred_lag134_flat",
    "pred_lag134_up",
    "pred_lag135_down",
    "pred_lag135_flat",
    "pred_lag135_up",
    "pred_lag136_down",
    "pred_lag136_flat",
    "pred_lag136_up",
    "pred_lag137_down",
    "pred_lag137_flat",
    "pred_lag137_up",
    "pred_lag138_down",
    "pred_lag138_flat",
    "pred_lag138_up",
    "pred_lag139_down",
    "pred_lag139_flat",
    "pred_lag139_up",
    "pred_lag140_down",
    "pred_lag140_flat",
    "pred_lag140_up",
    "pred_lag141_down",
    "pred_lag141_flat",
    "pred_lag141_up",
    "pred_lag142_down",
    "pred_lag142_flat",
    "pred_lag142_up",
    "pred_lag143_down",
    "pred_lag143_flat",
    "pred_lag143_up",
    "pred_lag144_down",
    "pred_lag144_flat",
    "pred_lag144_up",
    "pred_lag145_down",
    "pred_lag145_flat",
    "pred_lag145_up",
    "pred_lag146_down",
    "pred_lag146_flat",
    "pred_lag146_up",
    "pred_lag147_down",
    "pred_lag147_flat",
    "pred_lag147_up",
    "pred_lag148_down",
    "pred_lag148_flat",
    "pred_lag148_up",
    "pred_lag149_down",
    "pred_lag149_flat",
    "pred_lag149_up",
    "pred_lag150_down",
    "pred_lag150_flat",
    "pred_lag150_up",
    "pos_short",
    "pos_flat",
    "pos_long",
    "bars_in_pos_norm",
    "unrealized_return",
    "status_target_hit",
    "status_stop_hit"
  ],
  "stage1_extra_feature_names": [],
  "feature_shape": [
    11,
    150
  ],
  "evaluation_mode": "single_split",
  "split_mode": "ratio:0.4",
  "n_kept": 12000,
  "n_skipped": 254184,
  "train_samples": 7200,
  "test_samples": 4800,
  "stage1": {
    "accuracy": 0.9179166666666667,
    "balanced_accuracy": 0.5673509594760968,
    "confusion_matrix": [
      [
        4353,
        118
      ],
      [
        276,
        53
      ]
    ],
    "confusion_labels": [
      "flat",
      "trend"
    ],
    "classification_report": {
      "flat": {
        "precision": 0.9403758911211925,
        "recall": 0.9736076940281816,
        "f1-score": 0.9567032967032967,
        "support": 4471.0
      },
      "trend": {
        "precision": 0.30994152046783624,
        "recall": 0.16109422492401215,
        "f1-score": 0.212,
        "support": 329.0
      },
      "accuracy": 0.9179166666666667,
      "macro avg": {
        "precision": 0.6251587057945144,
        "recall": 0.5673509594760968,
        "f1-score": 0.5843516483516483,
        "support": 4800.0
      },
      "weighted avg": {
        "precision": 0.8971648686326604,
        "recall": 0.9179166666666667,
        "f1-score": 0.9056600915750914,
        "support": 4800.0
      }
    }
  },
  "stage2": {
    "accuracy": 0.6792452830188679,
    "balanced_accuracy": 0.5155228758169934,
    "confusion_matrix": [
      [
        1,
        16
      ],
      [
        1,
        35
      ]
    ],
    "confusion_labels": [
      "down",
      "up"
    ],
    "classification_report": {
      "down": {
        "precision": 0.5,
        "recall": 0.058823529411764705,
        "f1-score": 0.10526315789473684,
        "support": 17.0
      },
      "up": {
        "precision": 0.6862745098039216,
        "recall": 0.9722222222222222,
        "f1-score": 0.8045977011494253,
        "support": 36.0
      },
      "accuracy": 0.6792452830188679,
      "macro avg": {
        "precision": 0.5931372549019608,
        "recall": 0.5155228758169934,
        "f1-score": 0.45493042952208107,
        "support": 53.0
      },
      "weighted avg": {
        "precision": 0.6265260821309655,
        "recall": 0.6792452830188679,
        "f1-score": 0.5802828476526385,
        "support": 53.0
      }
    }
  },
  "full_confusion_matrix": [
    [
      1,
      75,
      16,
      0
    ],
    [
      8,
      4308,
      106,
      0
    ],
    [
      1,
      201,
      35,
      0
    ],
    [
      0,
      45,
      4,
      0
    ]
  ],
  "full_confusion_labels": [
    "down",
    "flat",
    "up",
    "risky"
  ],
  "directional_pnl": {
    "trades": 46,
    "total_pnl": 82.32000000000517,
    "avg_trade": 1.7895652173914167,
    "n_days": 6,
    "avg_trades_per_day": 7.666666666666667,
    "avg_day": 13.72000000000086,
    "positive_days_pct": 33.33333333333333,
    "max_drawdown": -66.93999999999778,
    "long": {
      "trades": 43,
      "wins": 17,
      "losses": 26,
      "win_rate": 39.53488372093023,
      "total_pnl": 67.25000000000455,
      "avg_trade": 1.5639534883721988
    },
    "short": {
      "trades": 3,
      "wins": 2,
      "losses": 1,
      "win_rate": 66.66666666666666,
      "total_pnl": 15.070000000000618,
      "avg_trade": 5.0233333333335395
    },
    "streaks": {
      "max_win_streak": 3,
      "max_loss_streak": 5,
      "current_win_streak": 0,
      "current_loss_streak": 1
    },
    "reverse_signal": {
      "trades": 4,
      "wins": 2,
      "losses": 2,
      "breakeven": 0,
      "avg_pnl": 3.3975000000000364,
      "win_rate_pct": 50.0,
      "loss_rate_pct": 50.0
    },
    "target_hit": {
      "trades": 3,
      "avg_pnl": 43.64000000000033
    },
    "timeout": {
      "trades": 22,
      "wins": 14,
      "losses": 8,
      "breakeven": 0,
      "avg_pnl": 6.445909090909274,
      "win_rate_pct": 63.63636363636363,
      "loss_rate_pct": 36.36363636363637
    },
    "all": {
      "trades": 46,
      "total_pnl": 82.32000000000517,
      "avg_trade": 1.7895652173914167,
      "median_trade": -2.719999999999345,
      "win_rate_pct": 41.30434782608695,
      "gross_profit": 326.2100000000037,
      "gross_loss": -243.8899999999985,
      "profit_factor": 1.3375292139899366,
      "best_trade": 53.5,
      "worst_trade": -12.0,
      "avg_win": 17.168947368421247,
      "avg_loss": -9.032962962962907,
      "max_win_streak": 3,
      "max_loss_streak": 5,
      "current_streak": 1,
      "current_win_streak": 0,
      "current_loss_streak": 1,
      "avg_duration_min": 29.891304347826086,
      "median_duration_min": 24.0,
      "min_duration_min": 0.0,
      "max_duration_min": 514.0,
      "n_days": 6,
      "avg_trades_per_day": 7.666666666666667,
      "avg_day": 13.72000000000086,
      "median_day": -4.659999999998945,
      "best_day": 82.10000000000218,
      "worst_day": -28.279999999998836,
      "positive_days_pct": 33.33333333333333,
      "trade_max_drawdown": -66.93999999999778,
      "daily_max_drawdown": -33.919999999997344,
      "exit_reason_counts": {
        "timeout": 22,
        "stop_loss": 17,
        "reverse_signal": 4,
        "target_hit": 3
      },
      "reverse_signal_stats": {
        "trades": 4,
        "wins": 2,
        "losses": 2,
        "breakeven": 0,
        "avg_pnl": 3.3975000000000364,
        "win_rate_pct": 50.0,
        "loss_rate_pct": 50.0
      },
      "target_hit_stats": {
        "trades": 3,
        "avg_pnl": 43.64000000000033
      },
      "timeout_stats": {
        "trades": 22,
        "wins": 14,
        "losses": 8,
        "breakeven": 0,
        "avg_pnl": 6.445909090909274,
        "win_rate_pct": 63.63636363636363,
        "loss_rate_pct": 36.36363636363637
      },
      "target_updates_mean": 1.0,
      "target_updates_median": 0.0,
      "target_updates_max": 9,
      "time_distribution": {
        "timezone_labels": {
          "hkt": "Asia/Hong_Kong",
          "ny": "America/New_York"
        },
        "by_weekday_hkt": [
          {
            "weekday_hkt": "Monday",
            "trades": 5,
            "total_pnl": -16.279999999998836,
            "avg_trade": -3.255999999999767,
            "win_rate_pct": 40.0
          },
          {
            "weekday_hkt": "Tuesday",
            "trades": 7,
            "total_pnl": -12.099999999999454,
            "avg_trade": -1.7285714285713507,
            "win_rate_pct": 42.857142857142854
          },
          {
            "weekday_hkt": "Wednesday",
            "trades": 14,
            "total_pnl": 28.61000000000149,
            "avg_trade": 2.043571428571535,
            "win_rate_pct": 50.0
          },
          {
            "weekday_hkt": "Thursday",
            "trades": 20,
            "total_pnl": 82.09000000000196,
            "avg_trade": 4.104500000000098,
            "win_rate_pct": 35.0
          }
        ],
        "by_hour_hkt": [
          {
            "hour_hkt": 1,
            "trades": 2,
            "total_pnl": -14.55999999999949,
            "avg_trade": -7.279999999999745,
            "win_rate_pct": 0.0
          },
          {
            "hour_hkt": 2,
            "trades": 2,
            "total_pnl": 3.6699999999991633,
            "avg_trade": 1.8349999999995816,
            "win_rate_pct": 50.0
          },
          {
            "hour_hkt": 3,
            "trades": 2,
            "total_pnl": -2.9799999999995634,
            "avg_trade": -1.4899999999997817,
            "win_rate_pct": 50.0
          },
          {
            "hour_hkt": 6,
            "trades": 2,
            "total_pnl": 0.2000000000007276,
            "avg_trade": 0.1000000000003638,
            "win_rate_pct": 50.0
          },
          {
            "hour_hkt": 8,
            "trades": 4,
            "total_pnl": -24.31999999999971,
            "avg_trade": -6.079999999999927,
            "win_rate_pct": 25.0
          },
          {
            "hour_hkt": 9,
            "trades": 7,
            "total_pnl": 12.949999999999818,
            "avg_trade": 1.849999999999974,
            "win_rate_pct": 42.857142857142854
          },
          {
            "hour_hkt": 10,
            "trades": 4,
            "total_pnl": 10.079999999999927,
            "avg_trade": 2.519999999999982,
            "win_rate_pct": 50.0
          },
          {
            "hour_hkt": 11,
            "trades": 1,
            "total_pnl": -2.8799999999991996,
            "avg_trade": -2.8799999999991996,
            "win_rate_pct": 0.0
          },
          {
            "hour_hkt": 12,
            "trades": 1,
            "total_pnl": -3.3599999999996726,
            "avg_trade": -3.3599999999996726,
            "win_rate_pct": 0.0
          },
          {
            "hour_hkt": 13,
            "trades": 2,
            "total_pnl": -20.159999999999854,
            "avg_trade": -10.079999999999927,
            "win_rate_pct": 0.0
          },
          {
            "hour_hkt": 14,
            "trades": 2,
            "total_pnl": 23.789999999999964,
            "avg_trade": 11.894999999999982,
            "win_rate_pct": 50.0
          },
          {
            "hour_hkt": 15,
            "trades": 3,
            "total_pnl": -9.979999999999563,
            "avg_trade": -3.326666666666521,
            "win_rate_pct": 33.33333333333333
          },
          {
            "hour_hkt": 16,
            "trades": 1,
            "total_pnl": 5.450000000000728,
            "avg_trade": 5.450000000000728,
            "win_rate_pct": 100.0
          },
          {
            "hour_hkt": 18,
            "trades": 1,
            "total_pnl": -4.3100000000004,
            "avg_trade": -4.3100000000004,
            "win_rate_pct": 0.0
          },
          {
            "hour_hkt": 21,
            "trades": 2,
            "total_pnl": 51.3100000000004,
            "avg_trade": 25.6550000000002,
            "win_rate_pct": 50.0
          },
          {
            "hour_hkt": 22,
            "trades": 9,
            "total_pnl": 61.10000000000127,
            "avg_trade": 6.78888888888903,
            "win_rate_pct": 66.66666666666666
          },
          {
            "hour_hkt": 23,
            "trades": 1,
            "total_pnl": -3.6799999999993815,
            "avg_trade": -3.6799999999993815,
            "win_rate_pct": 0.0
          }
        ],
        "by_hour_ny": [
          {
            "hour_ny": 0,
            "trades": 1,
            "total_pnl": -3.3599999999996726,
            "avg_trade": -3.3599999999996726,
            "win_rate_pct": 0.0
          },
          {
            "hour_ny": 1,
            "trades": 2,
            "total_pnl": -20.159999999999854,
            "avg_trade": -10.079999999999927,
            "win_rate_pct": 0.0
          },
          {
            "hour_ny": 2,
            "trades": 2,
            "total_pnl": 23.789999999999964,
            "avg_trade": 11.894999999999982,
            "win_rate_pct": 50.0
          },
          {
            "hour_ny": 3,
            "trades": 3,
            "total_pnl": -9.979999999999563,
            "avg_trade": -3.326666666666521,
            "win_rate_pct": 33.33333333333333
          },
          {
            "hour_ny": 4,
            "trades": 1,
            "total_pnl": 5.450000000000728,
            "avg_trade": 5.450000000000728,
            "win_rate_pct": 100.0
          },
          {
            "hour_ny": 6,
            "trades": 1,
            "total_pnl": -4.3100000000004,
            "avg_trade": -4.3100000000004,
            "win_rate_pct": 0.0
          },
          {
            "hour_ny": 9,
            "trades": 2,
            "total_pnl": 51.3100000000004,
            "avg_trade": 25.6550000000002,
            "win_rate_pct": 50.0
          },
          {
            "hour_ny": 10,
            "trades": 9,
            "total_pnl": 61.10000000000127,
            "avg_trade": 6.78888888888903,
            "win_rate_pct": 66.66666666666666
          },
          {
            "hour_ny": 11,
            "trades": 1,
            "total_pnl": -3.6799999999993815,
            "avg_trade": -3.6799999999993815,
            "win_rate_pct": 0.0
          },
          {
            "hour_ny": 13,
            "trades": 2,
            "total_pnl": -14.55999999999949,
            "avg_trade": -7.279999999999745,
            "win_rate_pct": 0.0
          },
          {
            "hour_ny": 14,
            "trades": 2,
            "total_pnl": 3.6699999999991633,
            "avg_trade": 1.8349999999995816,
            "win_rate_pct": 50.0
          },
          {
            "hour_ny": 15,
            "trades": 2,
            "total_pnl": -2.9799999999995634,
            "avg_trade": -1.4899999999997817,
            "win_rate_pct": 50.0
          },
          {
            "hour_ny": 18,
            "trades": 2,
            "total_pnl": 0.2000000000007276,
            "avg_trade": 0.1000000000003638,
            "win_rate_pct": 50.0
          },
          {
            "hour_ny": 20,
            "trades": 4,
            "total_pnl": -24.31999999999971,
            "avg_trade": -6.079999999999927,
            "win_rate_pct": 25.0
          },
          {
            "hour_ny": 21,
            "trades": 7,
            "total_pnl": 12.949999999999818,
            "avg_trade": 1.849999999999974,
            "win_rate_pct": 42.857142857142854
          },
          {
            "hour_ny": 22,
            "trades": 4,
            "total_pnl": 10.079999999999927,
            "avg_trade": 2.519999999999982,
            "win_rate_pct": 50.0
          },
          {
            "hour_ny": 23,
            "trades": 1,
            "total_pnl": -2.8799999999991996,
            "avg_trade": -2.8799999999991996,
            "win_rate_pct": 0.0
          }
        ],
        "by_session": [
          {
            "session": "Asia",
            "trades": 28,
            "total_pnl": -12.539999999997235,
            "avg_trade": -0.4478571428570441,
            "win_rate_pct": 35.714285714285715
          },
          {
            "session": "NY",
            "trades": 18,
            "total_pnl": 94.8600000000024,
            "avg_trade": 5.270000000000134,
            "win_rate_pct": 50.0
          }
        ],
        "weekday_hour_hkt_heatmap": {
          "Monday": {
            "06:00": {
              "trades": 2,
              "total_pnl": 0.2000000000007276,
              "avg_trade": 0.1000000000003638,
              "win_rate_pct": 50.0
            },
            "08:00": {
              "trades": 1,
              "total_pnl": -12.0,
              "avg_trade": -12.0,
              "win_rate_pct": 0.0
            },
            "10:00": {
              "trades": 1,
              "total_pnl": -9.930000000000291,
              "avg_trade": -9.930000000000291,
              "win_rate_pct": 0.0
            },
            "16:00": {
              "trades": 1,
              "total_pnl": 5.450000000000728,
              "avg_trade": 5.450000000000728,
              "win_rate_pct": 100.0
            }
          },
          "Tuesday": {
            "01:00": {
              "trades": 1,
              "total_pnl": -12.0,
              "avg_trade": -12.0,
              "win_rate_pct": 0.0
            },
            "10:00": {
              "trades": 1,
              "total_pnl": 13.920000000000073,
              "avg_trade": 13.920000000000073,
              "win_rate_pct": 100.0
            },
            "13:00": {
              "trades": 1,
              "total_pnl": -8.159999999999854,
              "avg_trade": -8.159999999999854,
              "win_rate_pct": 0.0
            },
            "14:00": {
              "trades": 1,
              "total_pnl": -1.3400000000001455,
              "avg_trade": -1.3400000000001455,
              "win_rate_pct": 0.0
            },
            "22:00": {
              "trades": 3,
              "total_pnl": -4.519999999999527,
              "avg_trade": -1.506666666666509,
              "win_rate_pct": 66.66666666666666
            }
          },
          "Wednesday": {
            "01:00": {
              "trades": 1,
              "total_pnl": -2.5599999999994907,
              "avg_trade": -2.5599999999994907,
              "win_rate_pct": 0.0
            },
            "03:00": {
              "trades": 2,
              "total_pnl": -2.9799999999995634,
              "avg_trade": -1.4899999999997817,
              "win_rate_pct": 50.0
            },
            "08:00": {
              "trades": 1,
              "total_pnl": -12.0,
              "avg_trade": -12.0,
              "win_rate_pct": 0.0
            },
            "09:00": {
              "trades": 2,
              "total_pnl": 21.829999999999927,
              "avg_trade": 10.914999999999964,
              "win_rate_pct": 100.0
            },
            "15:00": {
              "trades": 3,
              "total_pnl": -9.979999999999563,
              "avg_trade": -3.326666666666521,
              "win_rate_pct": 33.33333333333333
            },
            "18:00": {
              "trades": 1,
              "total_pnl": -4.3100000000004,
              "avg_trade": -4.3100000000004,
              "win_rate_pct": 0.0
            },
            "21:00": {
              "trades": 1,
              "total_pnl": -2.1899999999996,
              "avg_trade": -2.1899999999996,
              "win_rate_pct": 0.0
            },
            "22:00": {
              "trades": 3,
              "total_pnl": 40.80000000000018,
              "avg_trade": 13.60000000000006,
              "win_rate_pct": 100.0
            }
          },
          "Thursday": {
            "02:00": {
              "trades": 2,
              "total_pnl": 3.6699999999991633,
              "avg_trade": 1.8349999999995816,
              "win_rate_pct": 50.0
            },
            "08:00": {
              "trades": 2,
              "total_pnl": -0.31999999999970896,
              "avg_trade": -0.15999999999985448,
              "win_rate_pct": 50.0
            },
            "09:00": {
              "trades": 5,
              "total_pnl": -8.88000000000011,
              "avg_trade": -1.7760000000000218,
              "win_rate_pct": 20.0
            },
            "10:00": {
              "trades": 2,
              "total_pnl": 6.0900000000001455,
              "avg_trade": 3.0450000000000728,
              "win_rate_pct": 50.0
            },
            "11:00": {
              "trades": 1,
              "total_pnl": -2.8799999999991996,
              "avg_trade": -2.8799999999991996,
              "win_rate_pct": 0.0
            },
            "12:00": {
              "trades": 1,
              "total_pnl": -3.3599999999996726,
              "avg_trade": -3.3599999999996726,
              "win_rate_pct": 0.0
            },
            "13:00": {
              "trades": 1,
              "total_pnl": -12.0,
              "avg_trade": -12.0,
              "win_rate_pct": 0.0
            },
            "14:00": {
              "trades": 1,
              "total_pnl": 25.13000000000011,
              "avg_trade": 25.13000000000011,
              "win_rate_pct": 100.0
            },
            "21:00": {
              "trades": 1,
              "total_pnl": 53.5,
              "avg_trade": 53.5,
              "win_rate_pct": 100.0
            },
            "22:00": {
              "trades": 3,
              "total_pnl": 24.82000000000062,
              "avg_trade": 8.27333333333354,
              "win_rate_pct": 33.33333333333333
            },
            "23:00": {
              "trades": 1,
              "total_pnl": -3.6799999999993815,
              "avg_trade": -3.6799999999993815,
              "win_rate_pct": 0.0
            }
          }
        }
      }
    },
    "long_up": {
      "trades": 43,
      "total_pnl": 67.25000000000455,
      "avg_trade": 1.5639534883721988,
      "median_trade": -2.8799999999991996,
      "win_rate_pct": 39.53488372093023,
      "gross_profit": 302.9800000000032,
      "gross_loss": -235.72999999999865,
      "profit_factor": 1.2852840113689599,
      "best_trade": 53.5,
      "worst_trade": -12.0,
      "avg_win": 17.82235294117666,
      "avg_loss": -9.06653846153841,
      "max_win_streak": 3,
      "max_loss_streak": 5,
      "current_streak": 1,
      "current_win_streak": 0,
      "current_loss_streak": 1,
      "avg_duration_min": 31.232558139534884,
      "median_duration_min": 24.0,
      "min_duration_min": 0.0,
      "max_duration_min": 514.0,
      "n_days": 6,
      "avg_trades_per_day": 7.166666666666667,
      "avg_day": 11.20833333333409,
      "median_day": -0.839999999999236,
      "best_day": 82.10000000000218,
      "worst_day": -28.279999999998836,
      "positive_days_pct": 50.0,
      "trade_max_drawdown": -59.29999999999836,
      "daily_max_drawdown": -28.279999999998836,
      "exit_reason_counts": {
        "timeout": 22,
        "stop_loss": 17,
        "target_hit": 3,
        "reverse_signal": 1
      },
      "reverse_signal_stats": {
        "trades": 1,
        "wins": 0,
        "losses": 1,
        "breakeven": 0,
        "avg_pnl": -1.480000000000473,
        "win_rate_pct": 0.0,
        "loss_rate_pct": 100.0
      },
      "target_hit_stats": {
        "trades": 3,
        "avg_pnl": 43.64000000000033
      },
      "timeout_stats": {
        "trades": 22,
        "wins": 14,
        "losses": 8,
        "breakeven": 0,
        "avg_pnl": 6.445909090909274,
        "win_rate_pct": 63.63636363636363,
        "loss_rate_pct": 36.36363636363637
      },
      "target_updates_mean": 1.0232558139534884,
      "target_updates_median": 0.0,
      "target_updates_max": 9,
      "time_distribution": {
        "timezone_labels": {
          "hkt": "Asia/Hong_Kong",
          "ny": "America/New_York"
        },
        "by_weekday_hkt": [
          {
            "weekday_hkt": "Monday",
            "trades": 5,
            "total_pnl": -16.279999999998836,
            "avg_trade": -3.255999999999767,
            "win_rate_pct": 40.0
          },
          {
            "weekday_hkt": "Tuesday",
            "trades": 5,
            "total_pnl": -4.460000000000036,
            "avg_trade": -0.8920000000000072,
            "win_rate_pct": 40.0
          },
          {
            "weekday_hkt": "Wednesday",
            "trades": 13,
            "total_pnl": 5.900000000001455,
            "avg_trade": 0.4538461538462658,
            "win_rate_pct": 46.15384615384615
          },
          {
            "weekday_hkt": "Thursday",
            "trades": 20,
            "total_pnl": 82.09000000000196,
            "avg_trade": 4.104500000000098,
            "win_rate_pct": 35.0
          }
        ],
        "by_hour_hkt": [
          {
            "hour_hkt": 1,
            "trades": 2,
            "total_pnl": -14.55999999999949,
            "avg_trade": -7.279999999999745,
            "win_rate_pct": 0.0
          },
          {
            "hour_hkt": 2,
            "trades": 2,
            "total_pnl": 3.6699999999991633,
            "avg_trade": 1.8349999999995816,
            "win_rate_pct": 50.0
          },
          {
            "hour_hkt": 3,
            "trades": 2,
            "total_pnl": -2.9799999999995634,
            "avg_trade": -1.4899999999997817,
            "win_rate_pct": 50.0
          },
          {
            "hour_hkt": 6,
            "trades": 2,
            "total_pnl": 0.2000000000007276,
            "avg_trade": 0.1000000000003638,
            "win_rate_pct": 50.0
          },
          {
            "hour_hkt": 8,
            "trades": 4,
            "total_pnl": -24.31999999999971,
            "avg_trade": -6.079999999999927,
            "win_rate_pct": 25.0
          },
          {
            "hour_hkt": 9,
            "trades": 7,
            "total_pnl": 12.949999999999818,
            "avg_trade": 1.849999999999974,
            "win_rate_pct": 42.857142857142854
          },
          {
            "hour_hkt": 10,
            "trades": 4,
            "total_pnl": 10.079999999999927,
            "avg_trade": 2.519999999999982,
            "win_rate_pct": 50.0
          },
          {
            "hour_hkt": 11,
            "trades": 1,
            "total_pnl": -2.8799999999991996,
            "avg_trade": -2.8799999999991996,
            "win_rate_pct": 0.0
          },
          {
            "hour_hkt": 12,
            "trades": 1,
            "total_pnl": -3.3599999999996726,
            "avg_trade": -3.3599999999996726,
            "win_rate_pct": 0.0
          },
          {
            "hour_hkt": 13,
            "trades": 1,
            "total_pnl": -12.0,
            "avg_trade": -12.0,
            "win_rate_pct": 0.0
          },
          {
            "hour_hkt": 14,
            "trades": 2,
            "total_pnl": 23.789999999999964,
            "avg_trade": 11.894999999999982,
            "win_rate_pct": 50.0
          },
          {
            "hour_hkt": 15,
            "trades": 3,
            "total_pnl": -9.979999999999563,
            "avg_trade": -3.326666666666521,
            "win_rate_pct": 33.33333333333333
          },
          {
            "hour_hkt": 16,
            "trades": 1,
            "total_pnl": 5.450000000000728,
            "avg_trade": 5.450000000000728,
            "win_rate_pct": 100.0
          },
          {
            "hour_hkt": 18,
            "trades": 1,
            "total_pnl": -4.3100000000004,
            "avg_trade": -4.3100000000004,
            "win_rate_pct": 0.0
          },
          {
            "hour_hkt": 21,
            "trades": 2,
            "total_pnl": 51.3100000000004,
            "avg_trade": 25.6550000000002,
            "win_rate_pct": 50.0
          },
          {
            "hour_hkt": 22,
            "trades": 7,
            "total_pnl": 37.8700000000008,
            "avg_trade": 5.410000000000115,
            "win_rate_pct": 57.14285714285714
          },
          {
            "hour_hkt": 23,
            "trades": 1,
            "total_pnl": -3.6799999999993815,
            "avg_trade": -3.6799999999993815,
            "win_rate_pct": 0.0
          }
        ],
        "by_hour_ny": [
          {
            "hour_ny": 0,
            "trades": 1,
            "total_pnl": -3.3599999999996726,
            "avg_trade": -3.3599999999996726,
            "win_rate_pct": 0.0
          },
          {
            "hour_ny": 1,
            "trades": 1,
            "total_pnl": -12.0,
            "avg_trade": -12.0,
            "win_rate_pct": 0.0
          },
          {
            "hour_ny": 2,
            "trades": 2,
            "total_pnl": 23.789999999999964,
            "avg_trade": 11.894999999999982,
            "win_rate_pct": 50.0
          },
          {
            "hour_ny": 3,
            "trades": 3,
            "total_pnl": -9.979999999999563,
            "avg_trade": -3.326666666666521,
            "win_rate_pct": 33.33333333333333
          },
          {
            "hour_ny": 4,
            "trades": 1,
            "total_pnl": 5.450000000000728,
            "avg_trade": 5.450000000000728,
            "win_rate_pct": 100.0
          },
          {
            "hour_ny": 6,
            "trades": 1,
            "total_pnl": -4.3100000000004,
            "avg_trade": -4.3100000000004,
            "win_rate_pct": 0.0
          },
          {
            "hour_ny": 9,
            "trades": 2,
            "total_pnl": 51.3100000000004,
            "avg_trade": 25.6550000000002,
            "win_rate_pct": 50.0
          },
          {
            "hour_ny": 10,
            "trades": 7,
            "total_pnl": 37.8700000000008,
            "avg_trade": 5.410000000000115,
            "win_rate_pct": 57.14285714285714
          },
          {
            "hour_ny": 11,
            "trades": 1,
            "total_pnl": -3.6799999999993815,
            "avg_trade": -3.6799999999993815,
            "win_rate_pct": 0.0
          },
          {
            "hour_ny": 13,
            "trades": 2,
            "total_pnl": -14.55999999999949,
            "avg_trade": -7.279999999999745,
            "win_rate_pct": 0.0
          },
          {
            "hour_ny": 14,
            "trades": 2,
            "total_pnl": 3.6699999999991633,
            "avg_trade": 1.8349999999995816,
            "win_rate_pct": 50.0
          },
          {
            "hour_ny": 15,
            "trades": 2,
            "total_pnl": -2.9799999999995634,
            "avg_trade": -1.4899999999997817,
            "win_rate_pct": 50.0
          },
          {
            "hour_ny": 18,
            "trades": 2,
            "total_pnl": 0.2000000000007276,
            "avg_trade": 0.1000000000003638,
            "win_rate_pct": 50.0
          },
          {
            "hour_ny": 20,
            "trades": 4,
            "total_pnl": -24.31999999999971,
            "avg_trade": -6.079999999999927,
            "win_rate_pct": 25.0
          },
          {
            "hour_ny": 21,
            "trades": 7,
            "total_pnl": 12.949999999999818,
            "avg_trade": 1.849999999999974,
            "win_rate_pct": 42.857142857142854
          },
          {
            "hour_ny": 22,
            "trades": 4,
            "total_pnl": 10.079999999999927,
            "avg_trade": 2.519999999999982,
            "win_rate_pct": 50.0
          },
          {
            "hour_ny": 23,
            "trades": 1,
            "total_pnl": -2.8799999999991996,
            "avg_trade": -2.8799999999991996,
            "win_rate_pct": 0.0
          }
        ],
        "by_session": [
          {
            "session": "Asia",
            "trades": 27,
            "total_pnl": -4.379999999997381,
            "avg_trade": -0.1622222222221252,
            "win_rate_pct": 37.03703703703704
          },
          {
            "session": "NY",
            "trades": 16,
            "total_pnl": 71.63000000000193,
            "avg_trade": 4.4768750000001205,
            "win_rate_pct": 43.75
          }
        ],
        "weekday_hour_hkt_heatmap": {
          "Monday": {
            "06:00": {
              "trades": 2,
              "total_pnl": 0.2000000000007276,
              "avg_trade": 0.1000000000003638,
              "win_rate_pct": 50.0
            },
            "08:00": {
              "trades": 1,
              "total_pnl": -12.0,
              "avg_trade": -12.0,
              "win_rate_pct": 0.0
            },
            "10:00": {
              "trades": 1,
              "total_pnl": -9.930000000000291,
              "avg_trade": -9.930000000000291,
              "win_rate_pct": 0.0
            },
            "16:00": {
              "trades": 1,
              "total_pnl": 5.450000000000728,
              "avg_trade": 5.450000000000728,
              "win_rate_pct": 100.0
            }
          },
          "Tuesday": {
            "01:00": {
              "trades": 1,
              "total_pnl": -12.0,
              "avg_trade": -12.0,
              "win_rate_pct": 0.0
            },
            "10:00": {
              "trades": 1,
              "total_pnl": 13.920000000000073,
              "avg_trade": 13.920000000000073,
              "win_rate_pct": 100.0
            },
            "14:00": {
              "trades": 1,
              "total_pnl": -1.3400000000001455,
              "avg_trade": -1.3400000000001455,
              "win_rate_pct": 0.0
            },
            "22:00": {
              "trades": 2,
              "total_pnl": -5.039999999999964,
              "avg_trade": -2.519999999999982,
              "win_rate_pct": 50.0
            }
          },
          "Wednesday": {
            "01:00": {
              "trades": 1,
              "total_pnl": -2.5599999999994907,
              "avg_trade": -2.5599999999994907,
              "win_rate_pct": 0.0
            },
            "03:00": {
              "trades": 2,
              "total_pnl": -2.9799999999995634,
              "avg_trade": -1.4899999999997817,
              "win_rate_pct": 50.0
            },
            "08:00": {
              "trades": 1,
              "total_pnl": -12.0,
              "avg_trade": -12.0,
              "win_rate_pct": 0.0
            },
            "09:00": {
              "trades": 2,
              "total_pnl": 21.829999999999927,
              "avg_trade": 10.914999999999964,
              "win_rate_pct": 100.0
            },
            "15:00": {
              "trades": 3,
              "total_pnl": -9.979999999999563,
              "avg_trade": -3.326666666666521,
              "win_rate_pct": 33.33333333333333
            },
            "18:00": {
              "trades": 1,
              "total_pnl": -4.3100000000004,
              "avg_trade": -4.3100000000004,
              "win_rate_pct": 0.0
            },
            "21:00": {
              "trades": 1,
              "total_pnl": -2.1899999999996,
              "avg_trade": -2.1899999999996,
              "win_rate_pct": 0.0
            },
            "22:00": {
              "trades": 2,
              "total_pnl": 18.090000000000146,
              "avg_trade": 9.045000000000073,
              "win_rate_pct": 100.0
            }
          },
          "Thursday": {
            "02:00": {
              "trades": 2,
              "total_pnl": 3.6699999999991633,
              "avg_trade": 1.8349999999995816,
              "win_rate_pct": 50.0
            },
            "08:00": {
              "trades": 2,
              "total_pnl": -0.31999999999970896,
              "avg_trade": -0.15999999999985448,
              "win_rate_pct": 50.0
            },
            "09:00": {
              "trades": 5,
              "total_pnl": -8.88000000000011,
              "avg_trade": -1.7760000000000218,
              "win_rate_pct": 20.0
            },
            "10:00": {
              "trades": 2,
              "total_pnl": 6.0900000000001455,
              "avg_trade": 3.0450000000000728,
              "win_rate_pct": 50.0
            },
            "11:00": {
              "trades": 1,
              "total_pnl": -2.8799999999991996,
              "avg_trade": -2.8799999999991996,
              "win_rate_pct": 0.0
            },
            "12:00": {
              "trades": 1,
              "total_pnl": -3.3599999999996726,
              "avg_trade": -3.3599999999996726,
              "win_rate_pct": 0.0
            },
            "13:00": {
              "trades": 1,
              "total_pnl": -12.0,
              "avg_trade": -12.0,
              "win_rate_pct": 0.0
            },
            "14:00": {
              "trades": 1,
              "total_pnl": 25.13000000000011,
              "avg_trade": 25.13000000000011,
              "win_rate_pct": 100.0
            },
            "21:00": {
              "trades": 1,
              "total_pnl": 53.5,
              "avg_trade": 53.5,
              "win_rate_pct": 100.0
            },
            "22:00": {
              "trades": 3,
              "total_pnl": 24.82000000000062,
              "avg_trade": 8.27333333333354,
              "win_rate_pct": 33.33333333333333
            },
            "23:00": {
              "trades": 1,
              "total_pnl": -3.6799999999993815,
              "avg_trade": -3.6799999999993815,
              "win_rate_pct": 0.0
            }
          }
        }
      }
    },
    "short_down": {
      "trades": 3,
      "total_pnl": 15.070000000000618,
      "avg_trade": 5.0233333333335395,
      "median_trade": 0.5200000000004366,
      "win_rate_pct": 66.66666666666666,
      "gross_profit": 23.230000000000473,
      "gross_loss": -8.159999999999854,
      "profit_factor": 2.8468137254903048,
      "best_trade": 22.710000000000036,
      "worst_trade": -8.159999999999854,
      "avg_win": 11.615000000000236,
      "avg_loss": -8.159999999999854,
      "max_win_streak": 2,
      "max_loss_streak": 1,
      "current_streak": 2,
      "current_win_streak": 2,
      "current_loss_streak": 0,
      "avg_duration_min": 10.666666666666666,
      "median_duration_min": 6.0,
      "min_duration_min": 2.0,
      "max_duration_min": 24.0,
      "n_days": 2,
      "avg_trades_per_day": 1.5,
      "avg_day": 7.535000000000309,
      "median_day": 7.535000000000309,
      "best_day": 22.710000000000036,
      "worst_day": -7.639999999999418,
      "positive_days_pct": 50.0,
      "trade_max_drawdown": 0.0,
      "daily_max_drawdown": 0.0,
      "exit_reason_counts": {
        "reverse_signal": 3
      },
      "reverse_signal_stats": {
        "trades": 3,
        "wins": 2,
        "losses": 1,
        "breakeven": 0,
        "avg_pnl": 5.0233333333335395,
        "win_rate_pct": 66.66666666666666,
        "loss_rate_pct": 33.33333333333333
      },
      "target_hit_stats": {
        "trades": 0,
        "avg_pnl": null
      },
      "timeout_stats": {
        "trades": 0,
        "wins": 0,
        "losses": 0,
        "breakeven": 0,
        "avg_pnl": null,
        "win_rate_pct": null,
        "loss_rate_pct": null
      },
      "target_updates_mean": 0.6666666666666666,
      "target_updates_median": 1.0,
      "target_updates_max": 1,
      "time_distribution": {
        "timezone_labels": {
          "hkt": "Asia/Hong_Kong",
          "ny": "America/New_York"
        },
        "by_weekday_hkt": [
          {
            "weekday_hkt": "Tuesday",
            "trades": 2,
            "total_pnl": -7.639999999999418,
            "avg_trade": -3.819999999999709,
            "win_rate_pct": 50.0
          },
          {
            "weekday_hkt": "Wednesday",
            "trades": 1,
            "total_pnl": 22.710000000000036,
            "avg_trade": 22.710000000000036,
            "win_rate_pct": 100.0
          }
        ],
        "by_hour_hkt": [
          {
            "hour_hkt": 13,
            "trades": 1,
            "total_pnl": -8.159999999999854,
            "avg_trade": -8.159999999999854,
            "win_rate_pct": 0.0
          },
          {
            "hour_hkt": 22,
            "trades": 2,
            "total_pnl": 23.230000000000473,
            "avg_trade": 11.615000000000236,
            "win_rate_pct": 100.0
          }
        ],
        "by_hour_ny": [
          {
            "hour_ny": 1,
            "trades": 1,
            "total_pnl": -8.159999999999854,
            "avg_trade": -8.159999999999854,
            "win_rate_pct": 0.0
          },
          {
            "hour_ny": 10,
            "trades": 2,
            "total_pnl": 23.230000000000473,
            "avg_trade": 11.615000000000236,
            "win_rate_pct": 100.0
          }
        ],
        "by_session": [
          {
            "session": "Asia",
            "trades": 1,
            "total_pnl": -8.159999999999854,
            "avg_trade": -8.159999999999854,
            "win_rate_pct": 0.0
          },
          {
            "session": "NY",
            "trades": 2,
            "total_pnl": 23.230000000000473,
            "avg_trade": 11.615000000000236,
            "win_rate_pct": 100.0
          }
        ],
        "weekday_hour_hkt_heatmap": {
          "Tuesday": {
            "13:00": {
              "trades": 1,
              "total_pnl": -8.159999999999854,
              "avg_trade": -8.159999999999854,
              "win_rate_pct": 0.0
            },
            "22:00": {
              "trades": 1,
              "total_pnl": 0.5200000000004366,
              "avg_trade": 0.5200000000004366,
              "win_rate_pct": 100.0
            }
          },
          "Wednesday": {
            "22:00": {
              "trades": 1,
              "total_pnl": 22.710000000000036,
              "avg_trade": 22.710000000000036,
              "win_rate_pct": 100.0
            }
          }
        }
      }
    }
  },
  "trading_day_cutoff": {
    "timezone": "America/New_York",
    "hour": 17
  },
  "walkforward_config": null,
  "walkforward_cycles": [],
  "model_reuse": null,
  "cache_info": {
    "bars": {
      "enabled": false,
      "kind": "bars"
    },
    "dataset": {
      "enabled": false,
      "kind": "supervised_dataset"
    }
  }
}